xolmurodov/__init__.py
xolmurodov-0.1.0.dist-info/licenses/LICENSE
xolmurodov-0.1.0.dist-info/METADATA
xolmurodov-0.1.0.dist-info/WHEEL
xolmurodov-0.1.0.dist-info/top_level.txt
xolmurodov-0.1.0.dist-info/RECORD
