Metadata-Version: 2.4
Name: xolmurodov
Version: 0.1.0
Summary: A beautifully formatted resume of Xolmurodov Diyorbek as a Python package.
Author: diyorbekw
Author-email: diyorbek0143@gmail.com
Classifier: Programming Language :: Python :: 3
Classifier: License :: OSI Approved :: MIT License
Classifier: Operating System :: OS Independent
Requires-Python: >=3.7
License-File: LICENSE
Dynamic: author
Dynamic: author-email
Dynamic: classifier
Dynamic: license-file
Dynamic: requires-python
Dynamic: summary
